{
  "filename": "2025_sep_uob_creditcard_combined.pdf",
  "bank_name": "UOB",
  "card_last_4": "9651",
  "card_name": "PREFERRED PLATINUM VISA",
  "statement_date": "2025-09-02",
  "period_start": "2025-08-01",
  "period_end": "2025-08-28",
  "total_charges": 666.34,
  "transactions": [
    {
      "transaction_date": "2025-08-28",
      "merchant_name": "SHOPEE SINGAPORE MP",
      "raw_description": "SHOPEE SINGAPORE MP SINGAPORE",
      "amount": -3.04,
      "ccy_fee": null,
      "is_refund": true,
      "country_code": "SG",
      "location": "SINGAPORE",
      "categories": [],
      "foreign_currency_amount": null,
      "is_reward": false,
      "reward_type": null
    },
    {
      "transaction_date": "2025-08-04",
      "merchant_name": "GOOGLE*YOUTUBE MEMBER",
      "raw_description": "GOOGLE*YOUTUBE MEMBER G.CO/HELPPAY#",
      "amount": 30.0,
      "ccy_fee": null,
      "is_refund": false,
      "country_code": "XXXX",
      "location": "G.CO/HELPPAY#",
      "categories": [
        "subscriptions"
      ],
      "foreign_currency_amount": null,
      "is_reward": false,
      "reward_type": null
    },
    {
      "transaction_date": "2025-08-12",
      "merchant_name": "SHOPEE SINGAPORE MP",
      "raw_description": "SHOPEE SINGAPORE MP SINGAPORE",
      "amount": 59.6,
      "ccy_fee": null,
      "is_refund": false,
      "country_code": "SG",
      "location": "SINGAPORE",
      "categories": [],
      "foreign_currency_amount": null,
      "is_reward": false,
      "reward_type": null
    },
    {
      "transaction_date": "2025-08-23",
      "merchant_name": "PAYPAL *IHERB LLC",
      "raw_description": "PAYPAL *IHERB LLC 4029357733",
      "amount": 57.02,
      "ccy_fee": null,
      "is_refund": false,
      "country_code": "XXXX",
      "location": "4029357733",
      "categories": [
        "subscriptions"
      ],
      "foreign_currency_amount": null,
      "is_reward": false,
      "reward_type": null
    },
    {
      "transaction_date": "2025-08-23",
      "merchant_name": "Grab*",
      "raw_description": "Grab* A-897G25NWWGAHAV Singapore",
      "amount": 20.7,
      "ccy_fee": null,
      "is_refund": false,
      "country_code": "SG",
      "location": "Singapore",
      "categories": [],
      "foreign_currency_amount": null,
      "is_reward": false,
      "reward_type": null
    },
    {
      "transaction_date": "2025-08-23",
      "merchant_name": "Grab*",
      "raw_description": "Grab* A-898EBWBWWGCDAV Singapore",
      "amount": 41.6,
      "ccy_fee": null,
      "is_refund": false,
      "country_code": "SG",
      "location": "Singapore",
      "categories": [],
      "foreign_currency_amount": null,
      "is_reward": false,
      "reward_type": null
    },
    {
      "transaction_date": "2025-08-25",
      "merchant_name": "SHOPEE SINGAPO",
      "raw_description": "SHOPEE SINGAPO SINGAPORE",
      "amount": 100.86,
      "ccy_fee": null,
      "is_refund": false,
      "country_code": "SG",
      "location": "SINGAPORE",
      "categories": [],
      "foreign_currency_amount": null,
      "is_reward": false,
      "reward_type": null
    },
    {
      "transaction_date": "2025-08-25",
      "merchant_name": "SP KOHEPETS.COM.SG",
      "raw_description": "SP KOHEPETS.COM.SG SINGAPORE",
      "amount": 76.0,
      "ccy_fee": null,
      "is_refund": false,
      "country_code": "SG",
      "location": "SINGAPORE",
      "categories": [],
      "foreign_currency_amount": null,
      "is_reward": false,
      "reward_type": null
    },
    {
      "transaction_date": "2025-08-25",
      "merchant_name": "DON DON DONKI - NORTHPOIN",
      "raw_description": "DON DON DONKI - NORTHPOINSINGAPORE",
      "amount": 47.06,
      "ccy_fee": null,
      "is_refund": false,
      "country_code": "SG",
      "location": "SINGAPORE",
      "categories": [],
      "foreign_currency_amount": null,
      "is_reward": false,
      "reward_type": null
    },
    {
      "transaction_date": "2025-08-25",
      "merchant_name": "REDMAN BY PHOON HUAT A",
      "raw_description": "REDMAN BY PHOON HUAT A SINGAPORE",
      "amount": 21.7,
      "ccy_fee": null,
      "is_refund": false,
      "country_code": "SG",
      "location": "SINGAPORE",
      "categories": [],
      "foreign_currency_amount": null,
      "is_reward": false,
      "reward_type": null
    },
    {
      "transaction_date": "2025-08-26",
      "merchant_name": "GIANT-NORTHSHORE",
      "raw_description": "GIANT-NORTHSHORE Singapore",
      "amount": 18.9,
      "ccy_fee": null,
      "is_refund": false,
      "country_code": "SG",
      "location": "Singapore",
      "categories": [],
      "foreign_currency_amount": null,
      "is_reward": false,
      "reward_type": null
    },
    {
      "transaction_date": "2025-08-27",
      "merchant_name": "SHOPEE SINGAPO",
      "raw_description": "SHOPEE SINGAPO SINGAPORE",
      "amount": 74.2,
      "ccy_fee": null,
      "is_refund": false,
      "country_code": "SG",
      "location": "SINGAPORE",
      "categories": [],
      "foreign_currency_amount": null,
      "is_reward": false,
      "reward_type": null
    },
    {
      "transaction_date": "2025-08-27",
      "merchant_name": "DON DON DONKI-CLARKE QUAY",
      "raw_description": "DON DON DONKI-CLARKE QUAYSINGAPORE",
      "amount": 33.74,
      "ccy_fee": null,
      "is_refund": false,
      "country_code": "SG",
      "location": "SINGAPORE",
      "categories": [],
      "foreign_currency_amount": null,
      "is_reward": false,
      "reward_type": null
    },
    {
      "transaction_date": "2025-08-29",
      "merchant_name": "Grab*",
      "raw_description": "Grab* A-89U82BSWXCGBAV Singapore",
      "amount": 39.1,
      "ccy_fee": null,
      "is_refund": false,
      "country_code": "SG",
      "location": "Singapore",
      "categories": [],
      "foreign_currency_amount": null,
      "is_reward": false,
      "reward_type": null
    },
    {
      "transaction_date": "2025-08-29",
      "merchant_name": "Grab*",
      "raw_description": "Grab* A-89U82BSWXCGBAV Singapore",
      "amount": 1.7,
      "ccy_fee": null,
      "is_refund": false,
      "country_code": "SG",
      "location": "Singapore",
      "categories": [],
      "foreign_currency_amount": null,
      "is_reward": false,
      "reward_type": null
    },
    {
      "transaction_date": "2025-08-29",
      "merchant_name": "Grab*",
      "raw_description": "Grab* A-89VJVP7GX4D9AV Singapore",
      "amount": 43.2,
      "ccy_fee": null,
      "is_refund": false,
      "country_code": "SG",
      "location": "Singapore",
      "categories": [],
      "foreign_currency_amount": null,
      "is_reward": false,
      "reward_type": null
    },
    {
      "transaction_date": "2025-08-29",
      "merchant_name": "Grab*",
      "raw_description": "Grab* A-89VJVP7GX4D9AV Singapore",
      "amount": 4.0,
      "ccy_fee": null,
      "is_refund": false,
      "country_code": "SG",
      "location": "Singapore",
      "categories": [],
      "foreign_currency_amount": null,
      "is_reward": false,
      "reward_type": null
    }
  ],
  "cardholder_name": "foo_chi_jao"
}
