{
  "filename": "2025_jul_uob_creditcard_combined.pdf",
  "bank_name": "UOB",
  "card_last_4": "6691",
  "card_name": "LADY'S SOLITAIRE CARD",
  "cardholder_name": "foo_chi_jao",
  "statement_date": "2025-07-02",
  "period_start": "2025-06-02",
  "period_end": "2025-07-01",
  "total_charges": 1390.53,
  "transactions": [
    {
      "transaction_date": "2025-06-02",
      "merchant_name": "Nasi Lemak Ayam Taliwa",
      "raw_description": "Nasi Lemak Ayam Taliwa SINGAPORE",
      "amount": 6.8,
      "ccy_fee": null,
      "is_refund": false,
      "country_code": "SG",
      "location": "SINGAPORE",
      "categories": [],
      "foreign_currency_amount": null,
      "is_reward": false,
      "reward_type": null
    },
    {
      "transaction_date": "2025-06-02",
      "merchant_name": "AIRBNB * HMEQ9J3B9Z",
      "raw_description": "AIRBNB * HMEQ9J3B9Z 653-163-1004",
      "amount": 762.58,
      "ccy_fee": null,
      "is_refund": false,
      "country_code": "SG",
      "location": "653-163-1004",
      "categories": [
        "travel_accommodation"
      ],
      "foreign_currency_amount": null,
      "is_reward": false,
      "reward_type": null
    },
    {
      "transaction_date": "2025-06-07",
      "merchant_name": "Same Days Coffee Stand 292 JOO CHIAT",
      "raw_description": "Same Days Coffee Stand 292 JOO CHIAT",
      "amount": 8.0,
      "ccy_fee": null,
      "is_refund": false,
      "country_code": "SG",
      "location": "JOO CHIAT",
      "categories": [],
      "foreign_currency_amount": null,
      "is_reward": false,
      "reward_type": null
    },
    {
      "transaction_date": "2025-06-07",
      "merchant_name": "DOP3ST PTE LTD",
      "raw_description": "DOP3ST PTE LTD SINGAPORE",
      "amount": 26.0,
      "ccy_fee": null,
      "is_refund": false,
      "country_code": "SG",
      "location": "SINGAPORE",
      "categories": [],
      "foreign_currency_amount": null,
      "is_reward": false,
      "reward_type": null
    },
    {
      "transaction_date": "2025-06-07",
      "merchant_name": "KOHI ROASTERY LLP",
      "raw_description": "KOHI ROASTERY LLP SINGAPORE",
      "amount": 6.5,
      "ccy_fee": null,
      "is_refund": false,
      "country_code": "SG",
      "location": "SINGAPORE",
      "categories": [],
      "foreign_currency_amount": null,
      "is_reward": false,
      "reward_type": null
    },
    {
      "transaction_date": "2025-06-08",
      "merchant_name": "KURIYA JAPANESE MKT WA",
      "raw_description": "KURIYA JAPANESE MKT WA SINGAPORE",
      "amount": 12.8,
      "ccy_fee": null,
      "is_refund": false,
      "country_code": "SG",
      "location": "SINGAPORE",
      "categories": [],
      "foreign_currency_amount": null,
      "is_reward": false,
      "reward_type": null
    },
    {
      "transaction_date": "2025-06-08",
      "merchant_name": "PRATUNAM BY SOI THAI S",
      "raw_description": "PRATUNAM BY SOI THAI S SINGAPORE",
      "amount": 10.19,
      "ccy_fee": null,
      "is_refund": false,
      "country_code": "SG",
      "location": "SINGAPORE",
      "categories": [],
      "foreign_currency_amount": null,
      "is_reward": false,
      "reward_type": null
    },
    {
      "transaction_date": "2025-06-08",
      "merchant_name": "IKEA-RESTAURANT",
      "raw_description": "IKEA-RESTAURANT SINGAPORE",
      "amount": 37.4,
      "ccy_fee": null,
      "is_refund": false,
      "country_code": "SG",
      "location": "SINGAPORE",
      "categories": [],
      "foreign_currency_amount": null,
      "is_reward": false,
      "reward_type": null
    },
    {
      "transaction_date": "2025-06-10",
      "merchant_name": "TS/Sukiya - Punggol Co",
      "raw_description": "TS/Sukiya - Punggol Co Singapore",
      "amount": 16.7,
      "ccy_fee": null,
      "is_refund": false,
      "country_code": "SG",
      "location": "Singapore",
      "categories": [],
      "foreign_currency_amount": null,
      "is_reward": false,
      "reward_type": null
    },
    {
      "transaction_date": "2025-06-13",
      "merchant_name": "FOLKYARD-SG",
      "raw_description": "FOLKYARD-SG SINGAPORE",
      "amount": 16.0,
      "ccy_fee": null,
      "is_refund": false,
      "country_code": "SG",
      "location": "SINGAPORE",
      "categories": [],
      "foreign_currency_amount": null,
      "is_reward": false,
      "reward_type": null
    },
    {
      "transaction_date": "2025-06-13",
      "merchant_name": "FEI MOOKATA",
      "raw_description": "FEI MOOKATA SINGAPORE",
      "amount": 40.89,
      "ccy_fee": null,
      "is_refund": false,
      "country_code": "SG",
      "location": "SINGAPORE",
      "categories": [],
      "foreign_currency_amount": null,
      "is_reward": false,
      "reward_type": null
    },
    {
      "transaction_date": "2025-06-14",
      "merchant_name": "SANPOUTEI RAMEN-SHAW HSE",
      "raw_description": "SANPOUTEI RAMEN-SHAW HSE SINGAPORE",
      "amount": 38.37,
      "ccy_fee": null,
      "is_refund": false,
      "country_code": "SG",
      "location": "SINGAPORE",
      "categories": [],
      "foreign_currency_amount": null,
      "is_reward": false,
      "reward_type": null
    },
    {
      "transaction_date": "2025-06-14",
      "merchant_name": "MIRAKU",
      "raw_description": "MIRAKU SINGAPORE",
      "amount": 342.9,
      "ccy_fee": null,
      "is_refund": false,
      "country_code": "SG",
      "location": "SINGAPORE",
      "categories": [],
      "foreign_currency_amount": null,
      "is_reward": false,
      "reward_type": null
    },
    {
      "transaction_date": "2025-06-14",
      "merchant_name": "WWW.NICKVINA.COM",
      "raw_description": "WWW.NICKVINA.COM SINGAPORE",
      "amount": 14.0,
      "ccy_fee": null,
      "is_refund": false,
      "country_code": "SG",
      "location": "SINGAPORE",
      "categories": [],
      "foreign_currency_amount": null,
      "is_reward": false,
      "reward_type": null
    },
    {
      "transaction_date": "2025-06-14",
      "merchant_name": "MONIGIRI 1 PTE LTD",
      "raw_description": "MONIGIRI 1 PTE LTD N/A",
      "amount": 6.9,
      "ccy_fee": null,
      "is_refund": false,
      "country_code": "SG",
      "location": null,
      "categories": [],
      "foreign_currency_amount": null,
      "is_reward": false,
      "reward_type": null
    },
    {
      "transaction_date": "2025-06-15",
      "merchant_name": "CHATERAISE - OASIS T",
      "raw_description": "CHATERAISE - OASIS T SINGAPORE",
      "amount": 5.5,
      "ccy_fee": null,
      "is_refund": false,
      "country_code": "SG",
      "location": "SINGAPORE",
      "categories": [],
      "foreign_currency_amount": null,
      "is_reward": false,
      "reward_type": null
    },
    {
      "transaction_date": "2025-06-15",
      "merchant_name": "Burger King SG",
      "raw_description": "Burger King SG",
      "amount": 7.0,
      "ccy_fee": null,
      "is_refund": false,
      "country_code": "SG",
      "location": null,
      "categories": [],
      "foreign_currency_amount": null,
      "is_reward": false,
      "reward_type": null
    },
    {
      "transaction_date": "2025-06-15",
      "merchant_name": "Burger King SG",
      "raw_description": "Burger King SG",
      "amount": 6.95,
      "ccy_fee": null,
      "is_refund": false,
      "country_code": "SG",
      "location": null,
      "categories": [],
      "foreign_currency_amount": null,
      "is_reward": false,
      "reward_type": null
    },
    {
      "transaction_date": "2025-06-15",
      "merchant_name": "CAFE RED GINGER - IMM",
      "raw_description": "CAFE RED GINGER - IMM Singapore",
      "amount": 12.3,
      "ccy_fee": null,
      "is_refund": false,
      "country_code": "SG",
      "location": "Singapore",
      "categories": [],
      "foreign_currency_amount": null,
      "is_reward": false,
      "reward_type": null
    },
    {
      "transaction_date": "2025-07-01",
      "merchant_name": "McDonalds 930224",
      "raw_description": "McDonalds 930224 Singapore",
      "amount": 12.75,
      "ccy_fee": null,
      "is_refund": false,
      "country_code": "SG",
      "location": "Singapore",
      "categories": [],
      "foreign_currency_amount": null,
      "is_reward": false,
      "reward_type": null
    }
  ]
}
